ge/__init__.py
ge-0.0.5.dist-info/licenses/LICENSE
ge-0.0.5.dist-info/METADATA
ge-0.0.5.dist-info/WHEEL
ge-0.0.5.dist-info/top_level.txt
ge-0.0.5.dist-info/RECORD
