Metadata-Version: 2.4
Name: ge
Version: 0.0.5
Summary: Utils for training models
Home-page: https://github.com/t-c-w/ge
Author: Thor Whalen
License: apache-2.0
Platform: any
License-File: LICENSE
Dynamic: license-file
